{
	"name": "KP_ADF_Write_Metadata",
	"properties": {
		"linkedServiceName": {
			"referenceName": "KP_ADF_AzureBlobStorage",
			"type": "LinkedServiceReference"
		},
		"annotations": [],
		"type": "DelimitedText",
		"typeProperties": {
			"location": {
				"type": "AzureBlobStorageLocation",
				"container": "kp-targets"
			},
			"columnDelimiter": "|",
			"escapeChar": "\\",
			"firstRowAsHeader": true,
			"quoteChar": "\""
		},
		"schema": []
	},
	"type": "Microsoft.DataFactory/factories/datasets"
}